polars_access_mdbtools/__init__.py
polars_access_mdbtools/py.typed
polars_access_mdbtools-0.1.2.dist-info/METADATA
polars_access_mdbtools-0.1.2.dist-info/WHEEL
polars_access_mdbtools-0.1.2.dist-info/licenses/LICENSE
polars_access_mdbtools-0.1.2.dist-info/RECORD
