Metadata-Version: 2.4
Name: polars_access_mdbtools
Version: 0.1.2
Summary: A library for reading tables from an Access database into Polars dataframes, using mdbtools
Project-URL: Homepage, https://github.com/DeflateAwning/polars_access_mdbtools
Project-URL: Issues, https://github.com/DeflateAwning/polars_access_mdbtools/issues
Project-URL: License, https://github.com/DeflateAwning/polars_access_mdbtools/blob/main/LICENSE
Author: DeflateAwning
License-File: LICENSE
Keywords: access,database,dataframe,mdbtools,polars
Classifier: License :: OSI Approved :: MIT License
Classifier: Operating System :: OS Independent
Classifier: Programming Language :: Python :: 3
Requires-Python: >=3.11
Requires-Dist: polars>=1.20
